ebeer/__init__.py
ebeer/beer_classifier.py
ebeer/metadata.json
ebeer/trained_model.h5
ebeer-0.0.21.dist-info/LICENSE
ebeer-0.0.21.dist-info/METADATA
ebeer-0.0.21.dist-info/WHEEL
ebeer-0.0.21.dist-info/top_level.txt
ebeer-0.0.21.dist-info/RECORD
