Metadata-Version: 2.1
Name: ebeer
Version: 0.0.21
Summary: CNN Trained to predict brazilian beers
Author-email: diego vasque maldonado <diegoomal13@gmail.com>
Project-URL: Homepage, https://github.com/Diegoomal/proj_integrado_trabalho_final
Project-URL: Bug Tracker, https://github.com/Diegoomal/proj_integrado_trabalho_final/issues
Classifier: Programming Language :: Python :: 3
Classifier: License :: OSI Approved :: MIT License
Classifier: Operating System :: OS Independent
Requires-Python: >=3.8
License-File: LICENSE
Requires-Dist: numpy
Requires-Dist: tensorflow
Requires-Dist: Pillow
Requires-Dist: importlib-resources
